fastapi_profiler/__init__.py
fastapi_profiler/_version.py
fastapi_profiler/profiler.py
fastapi_profiler-1.4.1.dist-info/LICENSE
fastapi_profiler-1.4.1.dist-info/METADATA
fastapi_profiler-1.4.1.dist-info/WHEEL
fastapi_profiler-1.4.1.dist-info/top_level.txt
fastapi_profiler-1.4.1.dist-info/RECORD
